reliontomo/__init__.py
reliontomo/bibtex.py
reliontomo/constants.py
reliontomo/objects.py
reliontomo/protocols.conf
reliontomo/utils.py
reliontomo/wizards.py
reliontomo/cmd/__init__.py
reliontomo/cmd/compareStarFiles.py
reliontomo/convert/__init__.py
reliontomo/convert/convert30_tomo.py
reliontomo/convert/convert40_tomo.py
reliontomo/convert/convert50_tomo.py
reliontomo/convert/convertBase.py
reliontomo/protocols/__init__.py
reliontomo/protocols/protocol_3d_classify_subtomograms.py
reliontomo/protocols/protocol_base_import_from_star.py
reliontomo/protocols/protocol_base_make_pseusosubtomos_and_rec_particle.py
reliontomo/protocols/protocol_base_per_part_per_tilt.py
reliontomo/protocols/protocol_base_refine.py
reliontomo/protocols/protocol_base_relion.py
reliontomo/protocols/protocol_ctf_refine.py
reliontomo/protocols/protocol_de_novo_initial_model.py
reliontomo/protocols/protocol_edit_particles_star.py
reliontomo/protocols/protocol_import_coordinates_from_star.py
reliontomo/protocols/protocol_import_subtomograms_from_star.py
reliontomo/protocols/protocol_make_pseudo_subtomos.py
reliontomo/protocols/protocol_matching_coordinates.py
reliontomo/protocols/protocol_motion_corr.py
reliontomo/protocols/protocol_post_process.py
reliontomo/protocols/protocol_prepare_data.py
reliontomo/protocols/protocol_re5_base_extract_subtomos_and_rec_particle.py
reliontomo/protocols/protocol_re5_extract_subtomos.py
reliontomo/protocols/protocol_re5_rec_tomogram.py
reliontomo/protocols/protocol_re5_reconstruc_particle_from_ts.py
reliontomo/protocols/protocol_rec_particle_from_subtomograms.py
reliontomo/protocols/protocol_rec_tomogram.py
reliontomo/protocols/protocol_reconstruc_particle_from_ts.py
reliontomo/protocols/protocol_refine_subtomograms.py
reliontomo/protocols/protocol_tomo_frame_align.py
reliontomo/tests/__init__.py
reliontomo/tests/test_compare_star_files.py
reliontomo/tests/test_conversion.py
reliontomo/tests/test_import_star_files.py
reliontomo/tests/test_motion_correction.py
scipion_em_reliontomo-4.0.2.dist-info/LICENSE
scipion_em_reliontomo-4.0.2.dist-info/METADATA
scipion_em_reliontomo-4.0.2.dist-info/WHEEL
scipion_em_reliontomo-4.0.2.dist-info/entry_points.txt
scipion_em_reliontomo-4.0.2.dist-info/top_level.txt
scipion_em_reliontomo-4.0.2.dist-info/RECORD
